[
  {
    "__type__": "cc.Prefab",
    "_name": "boss",
    "_objFlags": 0,
    "_native": "",
    "data": {
      "__id__": 1
    },
    "optimizationPolicy": 0,
    "asyncLoadAssets": false
  },
  {
    "__type__": "cc.Node",
    "_name": "boss",
    "_objFlags": 0,
    "_parent": null,
    "_children": [],
    "_active": true,
    "_level": 1,
    "_components": [
      {
        "__id__": 2
      },
      {
        "__id__": 3
      }
    ],
    "_prefab": {
      "__id__": 4
    },
    "_opacity": 255,
    "_color": {
      "__type__": "cc.Color",
      "r": 255,
      "g": 255,
      "b": 255,
      "a": 255
    },
    "_contentSize": {
      "__type__": "cc.Size",
      "width": 200,
      "height": 120
    },
    "_anchorPoint": {
      "__type__": "cc.Vec2",
      "x": 0.5,
      "y": 0.5
    },
    "_position": {
      "__type__": "cc.Vec3",
      "x": 474,
      "y": 541,
      "z": 0
    },
    "_scale": {
      "__type__": "cc.Vec3",
      "x": 1,
      "y": 1,
      "z": 1
    },
    "_rotationX": 0,
    "_rotationY": 0,
    "_quat": {
      "__type__": "cc.Quat",
      "x": 0,
      "y": 0,
      "z": 0,
      "w": 1
    },
    "_skewX": 0,
    "_skewY": 0,
    "_zIndex": 0,
    "groupIndex": 0,
    "_id": ""
  },
  {
    "__type__": "cc.Sprite",
    "_name": "",
    "_objFlags": 0,
    "node": {
      "__id__": 1
    },
    "_enabled": true,
    "_srcBlendFactor": 770,
    "_dstBlendFactor": 771,
    "_spriteFrame": {
      "__uuid__": "00e63e0e-7556-4a78-896d-e9728c89878e"
    },
    "_type": 0,
    "_sizeMode": 0,
    "_fillType": 0,
    "_fillCenter": {
      "__type__": "cc.Vec2",
      "x": 0,
      "y": 0
    },
    "_fillStart": 0,
    "_fillRange": 0,
    "_isTrimmedMode": true,
    "_state": 0,
    "_atlas": null,
    "_id": "70RhO1g+9G8Y2CvSXh22C8"
  },
  {
    "__type__": "22143XCitVFyq1E65CMLtQz",
    "_name": "",
    "_objFlags": 0,
    "node": {
      "__id__": 1
    },
    "_enabled": true,
    "jumpHeight": 100,
    "jumpDuration": 0.5,
    "maxMoveSpeed": 400,
    "accel": 350,
    "bulletPrefab": {
      "__uuid__": "95377325-e5ac-470f-922c-20c05083535f"
    },
    "redBulletPrefab": {
      "__uuid__": "61d3733b-51ab-4315-9cd8-d03d572f69bf"
    },
    "_id": "ebx2k1pNBMia86dYP4WnO3"
  },
  {
    "__type__": "cc.PrefabInfo",
    "root": {
      "__id__": 1
    },
    "asset": {
      "__uuid__": "cdadc7a6-04ad-41cc-8015-9b42ea9cf461"
    },
    "fileId": "467VndWd5KrqmuvaxAjuvz",
    "sync": false
  }
]